{"definitions":{"Security Policy POST body":{"required":["name"],"properties":{"name":{"type":"string","description":"Policy Name","maximum":64},"based-on":{"type":"string","enum":["Create New","default","saml","sharepoint","sharepoint2013","owa","owa2010","owa2013","oracle"]}}}},"paths":{"/security-policies/{Policy Name}":{"delete":{"description":"","summary":"DELETE Information of Security Policy","tags":["Security Policy"],"parameters":[{"name":"Authorization","required":"true","description":"Login token","type":"string","in":"header"},{"in":"path","required":"true","name":"Policy Name","description":"Policy Name of Security Policy","type":"string"}],"produces":["application/json"],"responses":{"405":{"description":"Method Not Allowed."},"401":{"description":"Invalid Credentials."},"200":{"description":"Successfully deleted."},"500":{"description":"Internal Server Error."},"400":{"description":"Invalid Request."},"404":{"description":"Resource Not Found."}}}},"/security-policies":{"post":{"description":"","summary":"ADD Information of Security Policy","tags":["Security Policy"],"produces":["application/json"],"parameters":[{"in":"header","type":"string","description":"Login token","name":"Authorization","required":"true"},{"in":"body","schema":{"$ref":"#/definitions/Security Policy POST body"},"description":"Body Parameter of Security Policy","type":"string","required":"true","name":"Security Policy"}],"responses":{"500":{"description":"Internal Server Error."},"405":{"description":"Method Not Allowed."},"406":{"description":"JSON Data not acceptable."},"401":{"description":"Invalid Credentials."},"201":{"description":"Successfully created."},"404":{"description":"Resource Not Found."},"400":{"description":"Invalid Request."},"415":{"description":"Invalid JSON data specified."}}}},"/security-policies ":{"get":{"produces":["application/json"],"parameters":[{"in":"header","name":"Authorization","required":"true","type":"string","description":"Login token"},{"name":"groups","items":{"enum":["URL Protection","Tarpit Profile","Parameter Protection","Request Limits","Cloaking","URL Normalization","Cookie Security","Security Policy","Client Profile"],"types":"string"},"type":"array","description":"","collectionFormat":"multi","in":"query"},{"type":"integer","description":"","name":"limit","in":"query"},{"in":"query","description":"","type":"integer","name":"offset"},{"collectionFormat":"multi","in":"query","items":{"enum":["name"],"types":"string"},"description":"","type":"array","name":"parameters"}],"responses":{"400":{"description":"Invalid Request."},"404":{"description":"Resource Not Found."},"200":{"description":"Successful operation."},"500":{"description":"Internal Server Error."},"401":{"description":"Invalid Credentials."},"405":{"description":"Method Not Allowed."}},"tags":["Security Policy"],"summary":"FETCH Information of Security Policy","description":""}},"/security-policies/{Policy Name} ":{"put":{"description":"","tags":["Security Policy"],"summary":"EDIT Information of Security Policy","produces":["application/json"],"parameters":[{"in":"header","description":"Login token","type":"string","name":"Authorization","required":"true"},{"required":"true","name":"Policy Name","type":"string","description":"Policy Name of Security Policy","in":"path"},{"in":"body","type":"string","schema":{"$ref":"#/definitions/Security Policy PUT body"},"description":"Body Parameter of Security Policy","name":"Security Policy","required":"true"}],"responses":{"200":{"description":"Successfully updated."},"404":{"description":"Resource Not Found."},"400":{"description":"Invalid Request."},"415":{"description":"Invalid JSON data specified."},"500":{"description":"Internal Server Error."},"406":{"description":"JSON Data not acceptable."},"405":{"description":"Method Not Allowed."},"401":{"description":"Invalid Credentials."}}}},"/security-policies/{Policy Name}  ":{"get":{"description":"","responses":{"400":{"description":"Invalid Request."},"404":{"description":"Resource Not Found."},"200":{"description":"Successful operation."},"500":{"description":"Internal Server Error."},"401":{"description":"Invalid Credentials."},"405":{"description":"Method Not Allowed."}},"produces":["application/json"],"parameters":[{"in":"header","description":"Login token","type":"string","name":"Authorization","required":"true"},{"description":"Policy Name of Security Policy","type":"string","required":"true","name":"Policy Name","in":"path"},{"items":{"enum":["URL Protection","Tarpit Profile","Parameter Protection","Request Limits","Cloaking","URL Normalization","Cookie Security","Security Policy","Client Profile"],"types":"string"},"description":"","type":"array","name":"groups","in":"query","collectionFormat":"multi"},{"name":"parameters","type":"array","items":{"enum":["name"],"types":"string"},"description":"","collectionFormat":"multi","in":"query"}],"summary":"FETCH Information of Security Policy","tags":["Security Policy"]}}},"schemes":["http"],"tags":[{"name":"Security Policy"}],"info":{"version":"3.2.0","termsOfService":"http://barracuda.com","title":"Security Policy API"},"basePath":"/restapi/v3.2","components":{"schemas":{}},"host":"<WAF-IP/WAF-Domain>:8000","swagger":"2.0"}