{"definitions":{"Group PUT body":{"properties":{"service-group":{"description":"Service Group","type":"string"}},"required":["service-group"]},"Group POST body":{"required":["service-group"],"properties":{"service-group":{"description":"Service Group","type":"string"}}}},"paths":{"/vsites/{Vsite}/service-groups":{"get":{"description":"","responses":{"400":{"description":"Invalid Request."},"404":{"description":"Resource Not Found."},"200":{"description":"Successful operation."},"500":{"description":"Internal Server Error."},"401":{"description":"Invalid Credentials."},"405":{"description":"Method Not Allowed."}},"produces":["application/json"],"parameters":[{"type":"string","description":"Login token","name":"Authorization","required":"true","in":"header"},{"in":"path","type":"string","description":"Vsite of Group","required":"true","name":"Vsite"},{"in":"query","collectionFormat":"multi","name":"parameters","items":{"types":"string","enum":["service-group"]},"description":"","type":"array"}],"summary":"FETCH Information of Group","tags":["Group"]}},"/vsites/{Vsite}/service-groups ":{"post":{"description":"","responses":{"500":{"description":"Internal Server Error."},"405":{"description":"Method Not Allowed."},"406":{"description":"JSON Data not acceptable."},"401":{"description":"Invalid Credentials."},"201":{"description":"Successfully created."},"404":{"description":"Resource Not Found."},"400":{"description":"Invalid Request."},"415":{"description":"Invalid JSON data specified."}},"produces":["application/json"],"parameters":[{"in":"header","required":"true","name":"Authorization","type":"string","description":"Login token"},{"name":"Vsite","required":"true","description":"Vsite of Group","type":"string","in":"path"},{"name":"Group","required":"true","schema":{"$ref":"#/definitions/Group POST body"},"description":"Body Parameter of Group","type":"string","in":"body"}],"tags":["Group"],"summary":"ADD Information of Group"}},"/vsites/{Vsite}/service-groups/{Service Group} ":{"get":{"description":"","produces":["application/json"],"parameters":[{"type":"string","description":"Login token","required":"true","name":"Authorization","in":"header"},{"in":"path","description":"Vsite of Group","type":"string","name":"Vsite","required":"true"},{"name":"Service Group","required":"true","description":"Service Group of Group","type":"string","in":"path"},{"in":"query","collectionFormat":"multi","type":"array","items":{"types":"string","enum":["service-group"]},"description":"","name":"parameters"}],"responses":{"400":{"description":"Invalid Request."},"404":{"description":"Resource Not Found."},"200":{"description":"Successful operation."},"500":{"description":"Internal Server Error."},"401":{"description":"Invalid Credentials."},"405":{"description":"Method Not Allowed."}},"tags":["Group"],"summary":"FETCH Information of Group"}},"/vsites/{Vsite}/service-groups/{Service Group}  ":{"put":{"tags":["Group"],"summary":"EDIT Information of Group","parameters":[{"in":"header","description":"Login token","type":"string","name":"Authorization","required":"true"},{"in":"path","required":"true","name":"Vsite","description":"Vsite of Group","type":"string"},{"in":"path","description":"Service Group of Group","type":"string","name":"Service Group","required":"true"},{"in":"body","name":"Group","required":"true","description":"Body Parameter of Group","schema":{"$ref":"#/definitions/Group PUT body"},"type":"string"}],"produces":["application/json"],"responses":{"200":{"description":"Successfully updated."},"404":{"description":"Resource Not Found."},"400":{"description":"Invalid Request."},"415":{"description":"Invalid JSON data specified."},"500":{"description":"Internal Server Error."},"406":{"description":"JSON Data not acceptable."},"405":{"description":"Method Not Allowed."},"401":{"description":"Invalid Credentials."}},"description":""}},"/vsites/{Vsite}/service-groups/{Service Group}":{"delete":{"summary":"DELETE Information of Group","tags":["Group"],"produces":["application/json"],"parameters":[{"in":"header","description":"Login token","type":"string","required":"true","name":"Authorization"},{"name":"Vsite","required":"true","type":"string","description":"Vsite of Group","in":"path"},{"in":"path","type":"string","description":"Service Group of Group","required":"true","name":"Service Group"}],"responses":{"405":{"description":"Method Not Allowed."},"401":{"description":"Invalid Credentials."},"200":{"description":"Successfully deleted."},"500":{"description":"Internal Server Error."},"400":{"description":"Invalid Request."},"404":{"description":"Resource Not Found."}},"description":""}}},"schemes":["http"],"components":{"schemas":{}},"host":"<WAF-IP/WAF-Domain>:8000","swagger":"2.0","tags":[{"name":"Group"}],"info":{"termsOfService":"http://barracuda.com","title":"Group API","version":"3.2.0"},"basePath":"/restapi/v3.2"}