{"basePath":"/restapi/v3.2","tags":[{"name":"ng firewall"}],"info":{"version":"3.2.0","title":"ng firewall API","termsOfService":"http://barracuda.com"},"swagger":"2.0","host":"<WAF-IP/WAF-Domain>:8000","components":{"schemas":{}},"paths":{"/system/ng-firewall ":{"put":{"parameters":[{"in":"header","description":"Login token","type":"string","required":"true","name":"Authorization"},{"in":"body","type":"string","schema":{"$ref":"#/definitions/ng firewall PUT body"},"description":"Body Parameter of ng firewall","name":"ng firewall","required":"true"}],"produces":["application/json"],"responses":{"200":{"description":"Successfully updated."},"404":{"description":"Resource Not Found."},"400":{"description":"Invalid Request."},"415":{"description":"Invalid JSON data specified."},"500":{"description":"Internal Server Error."},"406":{"description":"JSON Data not acceptable."},"405":{"description":"Method Not Allowed."},"401":{"description":"Invalid Credentials."}},"summary":"EDIT Information of ng firewall","tags":["ng firewall"],"description":""}},"/system/ng-firewall":{"get":{"summary":"FETCH Information of ng firewall","tags":["ng firewall"],"parameters":[{"description":"Login token","type":"string","required":"true","name":"Authorization","in":"header"},{"in":"query","collectionFormat":"multi","items":{"types":"string","enum":["port","server","username"]},"description":"","type":"array","name":"parameters"}],"produces":["application/json"],"responses":{"400":{"description":"Invalid Request."},"404":{"description":"Resource Not Found."},"200":{"description":"Successful operation."},"500":{"description":"Internal Server Error."},"401":{"description":"Invalid Credentials."},"405":{"description":"Method Not Allowed."}},"description":""}}},"schemes":["http"],"definitions":{"ng firewall PUT body":{"properties":{"username":{"description":"Server Username","type":"string"},"port":{"minimum":1,"type":"integer","description":"Server Port","maxmium":65535},"password":{"type":"string","description":"Server Password"},"server":{"type":"string","description":"Server Name/IP"}}},"ng firewall POST body":{"properties":{"username":{"type":"string","description":"Server Username"},"port":{"description":"Server Port","type":"integer","maxmium":65535,"minimum":1},"password":{"description":"Server Password","type":"string"},"server":{"type":"string","description":"Server Name/IP"}}}}}